{
  "content": [
    {
      "content": null,
      "created": "2024-02-24T00:54:35.738422Z",
      "format": null,
      "last_modified": "2024-02-24T00:54:15.586351Z",
      "mimetype": null,
      "name": "data-science-python-multiprocessing.ipynb",
      "path": "data-science-python-multiprocessing.ipynb",
      "size": 19066,
      "type": "notebook",
      "writable": true
    },
    {
      "content": null,
      "created": "2024-02-24T00:54:35.734422Z",
      "format": null,
      "last_modified": "2024-02-24T00:54:15.578351Z",
      "mimetype": null,
      "name": "data-science-python-glob.ipynb",
      "path": "data-science-python-glob.ipynb",
      "size": 9468,
      "type": "notebook",
      "writable": true
    },
    {
      "content": null,
      "created": "2024-02-24T00:54:35.734422Z",
      "format": null,
      "last_modified": "2024-02-24T00:54:15.566351Z",
      "mimetype": null,
      "name": "data-science-python-basics-recap.ipynb",
      "path": "data-science-python-basics-recap.ipynb",
      "size": 30699,
      "type": "notebook",
      "writable": true
    },
    {
      "content": null,
      "created": "2024-02-24T00:54:35.738422Z",
      "format": null,
      "last_modified": "2024-02-24T00:54:15.582351Z",
      "mimetype": null,
      "name": "data-science-python-math.ipynb",
      "path": "data-science-python-math.ipynb",
      "size": 28206,
      "type": "notebook",
      "writable": true
    },
    {
      "content": null,
      "created": "2024-02-24T00:54:35.738422Z",
      "format": null,
      "last_modified": "2024-02-24T00:54:15.590351Z",
      "mimetype": null,
      "name": "data-science-python-testing.ipynb",
      "path": "data-science-python-testing.ipynb",
      "size": 22271,
      "type": "notebook",
      "writable": true
    },
    {
      "content": null,
      "created": "2024-02-24T00:54:35.738422Z",
      "format": null,
      "last_modified": "2024-02-24T00:54:15.594351Z",
      "mimetype": null,
      "name": "data-science-python-types.ipynb",
      "path": "data-science-python-types.ipynb",
      "size": 29250,
      "type": "notebook",
      "writable": true
    },
    {
      "content": null,
      "created": "2024-02-24T00:54:35.734422Z",
      "format": null,
      "last_modified": "2024-02-24T00:54:15.562351Z",
      "mimetype": null,
      "name": "data-science-python-advanced-np-pd.ipynb",
      "path": "data-science-python-advanced-np-pd.ipynb",
      "size": 61286,
      "type": "notebook",
      "writable": true
    },
    {
      "content": null,
      "created": "2024-02-24T00:54:35.738422Z",
      "format": null,
      "last_modified": "2024-02-24T00:54:15.586351Z",
      "mimetype": null,
      "name": "data-science-python-plotting.ipynb",
      "path": "data-science-python-plotting.ipynb",
      "size": 20385,
      "type": "notebook",
      "writable": true
    },
    {
      "content": null,
      "created": "2024-02-24T00:54:35.738422Z",
      "format": null,
      "last_modified": "2024-02-24T00:54:15.598351Z",
      "mimetype": null,
      "name": "data-science-python-typing.ipynb",
      "path": "data-science-python-typing.ipynb",
      "size": 35829,
      "type": "notebook",
      "writable": true
    },
    {
      "content": null,
      "created": "2024-02-24T00:54:35.738422Z",
      "format": null,
      "last_modified": "2024-02-24T00:54:15.582351Z",
      "mimetype": null,
      "name": "data-science-python-loops.ipynb",
      "path": "data-science-python-loops.ipynb",
      "size": 45142,
      "type": "notebook",
      "writable": true
    },
    {
      "content": null,
      "created": "2024-02-24T00:54:35.734422Z",
      "format": null,
      "last_modified": "2024-02-24T00:54:15.570351Z",
      "mimetype": null,
      "name": "data-science-python-exceptions.ipynb",
      "path": "data-science-python-exceptions.ipynb",
      "size": 12059,
      "type": "notebook",
      "writable": true
    },
    {
      "content": null,
      "created": "2024-02-24T00:54:35.734422Z",
      "format": null,
      "last_modified": "2024-02-24T00:54:15.562351Z",
      "mimetype": null,
      "name": "data-science-python-basics.ipynb",
      "path": "data-science-python-basics.ipynb",
      "size": 112180,
      "type": "notebook",
      "writable": true
    },
    {
      "content": null,
      "created": "2024-02-24T00:54:35.734422Z",
      "format": null,
      "last_modified": "2024-02-24T00:54:15.574351Z",
      "mimetype": null,
      "name": "data-science-python-functions.ipynb",
      "path": "data-science-python-functions.ipynb",
      "size": 26274,
      "type": "notebook",
      "writable": true
    },
    {
      "content": null,
      "created": "2024-02-24T00:54:35.738422Z",
      "format": null,
      "last_modified": "2024-02-24T00:54:15.590351Z",
      "mimetype": null,
      "name": "data-science-python-subprocess.ipynb",
      "path": "data-science-python-subprocess.ipynb",
      "size": 23107,
      "type": "notebook",
      "writable": true
    },
    {
      "content": null,
      "created": "2024-02-24T00:54:35.738422Z",
      "format": null,
      "last_modified": "2024-02-24T00:54:15.578351Z",
      "mimetype": null,
      "name": "data-science-python-iterables.ipynb",
      "path": "data-science-python-iterables.ipynb",
      "size": 68475,
      "type": "notebook",
      "writable": true
    },
    {
      "content": null,
      "created": "2024-02-24T00:54:35.734422Z",
      "format": null,
      "last_modified": "2024-02-24T00:54:15.570351Z",
      "mimetype": null,
      "name": "data-science-python-files.ipynb",
      "path": "data-science-python-files.ipynb",
      "size": 43044,
      "type": "notebook",
      "writable": true
    },
    {
      "content": null,
      "created": "2024-02-24T00:54:35.734422Z",
      "format": null,
      "last_modified": "2024-02-24T00:54:15.574351Z",
      "mimetype": null,
      "name": "data-science-python-flow.ipynb",
      "path": "data-science-python-flow.ipynb",
      "size": 35850,
      "type": "notebook",
      "writable": true
    }
  ],
  "created": "2024-02-24T00:54:35.738422Z",
  "format": "json",
  "last_modified": "2024-02-24T00:54:35.738422Z",
  "mimetype": null,
  "name": "",
  "path": "",
  "size": null,
  "type": "directory",
  "writable": true
}